README
Captcha/Base.py
Captcha/File.py
Captcha/Words.py
Captcha/__init__.py
Captcha/Visual/Backgrounds.py
Captcha/Visual/Base.py
Captcha/Visual/Distortions.py
Captcha/Visual/Pictures.py
Captcha/Visual/Tests.py
Captcha/Visual/Text.py
Captcha/Visual/__init__.py
PyCAPTCHA.egg-info/PKG-INFO
PyCAPTCHA.egg-info/SOURCES.txt
PyCAPTCHA.egg-info/top_level.txt
