Metadata-Version: 1.0
Name: PyCAPTCHA
Version: 0.4
Summary: A Python framework for CAPTCHA tests
Home-page: UNKNOWN
Author: Micah Dowty
Author-email: micah@navi.cx
License: MIT
Platform: UNKNOWN
